adafruit_fram.py
adafruit_circuitpython_fram-1.3.27.dist-info/licenses/LICENSE
adafruit_circuitpython_fram-1.3.27.dist-info/METADATA
adafruit_circuitpython_fram-1.3.27.dist-info/WHEEL
adafruit_circuitpython_fram-1.3.27.dist-info/top_level.txt
adafruit_circuitpython_fram-1.3.27.dist-info/RECORD
